Metadata-Version: 2.1
Name: odoo14-addon-passport_expiration
Version: 14.0.0.1.1.dev6
Summary: Adds an expiration date for passports
Home-page: https://github.com/OCA/vertical-travel
Author: Savoir-faire Linux,Odoo Community Association (OCA)
Author-email: support@odoo-community.org
License: AGPL-3
Classifier: Programming Language :: Python
Classifier: Framework :: Odoo
Classifier: Framework :: Odoo :: 14.0
Classifier: License :: OSI Approved :: GNU Affero General Public License v3
Requires-Python: >=3.6
Requires-Dist: odoo<14.1dev,>=14.0a
